Workbook

Sheet Récapitulatif
A1: MADAPORC — Suivi des tâches & fonctions par membre
A4: Légende : | B4: Terminé | C4: En cours | D4: Pas fini
A6: Membre | B6: Binôme | C6: Rôle / Module(s) | D6: Fonctions OK | E6: Avanc. | F6: Durée totale (h) | G6: Heures faites (h) | H6: Heures restantes (h)
A7: MIARO — RAJAONSON Ny Andry Miaro | B7: Binôme 1 (avec Davida) | C7: Socle technique & intégration (fichiers communs) + (suite) Dépenses | D7: =COUNTIF(MIARO!$G$7:$G$24,"Terminé")&"/"&COUNT(MIARO!$A$7:$A$24) -> 18/18 | E7: =IFERROR((SUMIF(MIARO!$G$7:$G$24,"Terminé",MIARO!$F$7:$F$24)+0.5*SUMIF(MIARO!$G$7:$G$24,"En cours",MIARO!$F$7:$F$24))/SUM(MIARO!$F$7:$F$24),0) -> 1 | F7: =SUM(MIARO!$F$7:$F$24)/60 -> 7.3333333 | G7: =(SUMIF(MIARO!$G$7:$G$24,"Terminé",MIARO!$F$7:$F$24)+0.5*SUMIF(MIARO!$G$7:$G$24,"En cours",MIARO!$F$7:$F$24))/60 -> 7.3333333 | H7: =(SUMIF(MIARO!$G$7:$G$24,"Pas fini",MIARO!$F$7:$F$24)+0.5*SUMIF(MIARO!$G$7:$G$24,"En cours",MIARO!$F$7:$F$24))/60 -> 0
A8: DAVIDA — Davida Fiderana | B8: Binôme 1 (avec Miaro) | C8: Authentification & utilisateurs + (suite) Clients | D8: =COUNTIF(DAVIDA!$G$7:$G$29,"Terminé")&"/"&COUNT(DAVIDA!$A$7:$A$29) -> 23/23 | E8: =IFERROR((SUMIF(DAVIDA!$G$7:$G$29,"Terminé",DAVIDA!$F$7:$F$29)+0.5*SUMIF(DAVIDA!$G$7:$G$29,"En cours",DAVIDA!$F$7:$F$29))/SUM(DAVIDA!$F$7:$F$29),0) -> 1 | F8: =SUM(DAVIDA!$F$7:$F$29)/60 -> 16.583333 | G8: =(SUMIF(DAVIDA!$G$7:$G$29,"Terminé",DAVIDA!$F$7:$F$29)+0.5*SUMIF(DAVIDA!$G$7:$G$29,"En cours",DAVIDA!$F$7:$F$29))/60 -> 16.583333 | H8: =(SUMIF(DAVIDA!$G$7:$G$29,"Pas fini",DAVIDA!$F$7:$F$29)+0.5*SUMIF(DAVIDA!$G$7:$G$29,"En cours",DAVIDA!$F$7:$F$29))/60 -> 0
A9: FANILO — Fanilo Tsito | B9: Binôme 2 (avec Nomena) | C9: Lots de porcs + mouvements d'effectif + (suite) Ventes | D9: =COUNTIF(FANILO!$G$7:$G$26,"Terminé")&"/"&COUNT(FANILO!$A$7:$A$26) -> 20/20 | E9: =IFERROR((SUMIF(FANILO!$G$7:$G$26,"Terminé",FANILO!$F$7:$F$26)+0.5*SUMIF(FANILO!$G$7:$G$26,"En cours",FANILO!$F$7:$F$26))/SUM(FANILO!$F$7:$F$26),0) -> 1 | F9: =SUM(FANILO!$F$7:$F$26)/60 -> 23.333333 | G9: =(SUMIF(FANILO!$G$7:$G$26,"Terminé",FANILO!$F$7:$F$26)+0.5*SUMIF(FANILO!$G$7:$G$26,"En cours",FANILO!$F$7:$F$26))/60 -> 23.333333 | H9: =(SUMIF(FANILO!$G$7:$G$26,"Pas fini",FANILO!$F$7:$F$26)+0.5*SUMIF(FANILO!$G$7:$G$26,"En cours",FANILO!$F$7:$F$26))/60 -> 0
A10: NOMENA — Andriantsiferana Sarobidy | B10: Binôme 2 (avec Fanilo) | C10: Pesées des lots + Santé (pas de part dans la suite) | D10: =COUNTIF(NOMENA!$G$7:$G$19,"Terminé")&"/"&COUNT(NOMENA!$A$7:$A$19) -> 13/13 | E10: =IFERROR((SUMIF(NOMENA!$G$7:$G$19,"Terminé",NOMENA!$F$7:$F$19)+0.5*SUMIF(NOMENA!$G$7:$G$19,"En cours",NOMENA!$F$7:$F$19))/SUM(NOMENA!$F$7:$F$19),0) -> 1 | F10: =SUM(NOMENA!$F$7:$F$19)/60 -> 12.5 | G10: =(SUMIF(NOMENA!$G$7:$G$19,"Terminé",NOMENA!$F$7:$F$19)+0.5*SUMIF(NOMENA!$G$7:$G$19,"En cours",NOMENA!$F$7:$F$19))/60 -> 12.5 | H10: =(SUMIF(NOMENA!$G$7:$G$19,"Pas fini",NOMENA!$F$7:$F$19)+0.5*SUMIF(NOMENA!$G$7:$G$19,"En cours",NOMENA!$F$7:$F$19))/60 -> 0
A11: TSANTA — Tsanta Finaritra (Noahmathieu) | B11: Binôme 3 (avec Mickaella) | C11: Création & suivi initial du groupe de reproduction + (suite) Import / Export | D11: =COUNTIF(TSANTA!$G$7:$G$24,"Terminé")&"/"&COUNT(TSANTA!$A$7:$A$24) -> 18/18 | E11: =E10 -> 1 | F11: =SUM(TSANTA!$F$7:$F$24)/60 -> 16.5 | G11: =(SUMIF(TSANTA!$G$7:$G$24,"Terminé",TSANTA!$F$7:$F$24)+0.5*SUMIF(TSANTA!$G$7:$G$24,"En cours",TSANTA!$F$7:$F$24))/60 -> 16.5 | H11: =H10 -> 0
A12: MICKAELLA — Andriamarondraibe | B12: Binôme 3 (avec Tsanta) | C12: Détail groupe, confirmation mise bas & lot naissance + (suite) Rapports financiers | D12: =COUNTIF(MICKAELLA!$G$7:$G$27,"Terminé")&"/"&COUNT(MICKAELLA!$A$7:$A$27) -> 21/21 | E12: =IFERROR((SUMIF(MICKAELLA!$G$7:$G$27,"Terminé",MICKAELLA!$F$7:$F$27)+0.5*SUMIF(MICKAELLA!$G$7:$G$27,"En cours",MICKAELLA!$F$7:$F$27))/SUM(MICKAELLA!$F$7:$F$27),0) -> 1 | F12: =SUM(MICKAELLA!$F$7:$F$27)/60 -> 12.666667 | G12: =(SUMIF(MICKAELLA!$G$7:$G$27,"Terminé",MICKAELLA!$F$7:$F$27)+0.5*SUMIF(MICKAELLA!$G$7:$G$27,"En cours",MICKAELLA!$F$7:$F$27))/60 -> 12.666667 | H12: =(SUMIF(MICKAELLA!$G$7:$G$27,"Pas fini",MICKAELLA!$F$7:$F$27)+0.5*SUMIF(MICKAELLA!$G$7:$G$27,"En cours",MICKAELLA!$F$7:$F$27))/60 -> 0
A13: MANOA — Aina Manoa Rajoel | B13: Binôme 4 (avec Noah) | C13: Analyse reproductive & formules métier + (suite) Mouvements de stock alimentaire | D13: =COUNTIF(MANOA!$G$7:$G$25,"Terminé")&"/"&COUNT(MANOA!$A$7:$A$25) -> 19/19 | E13: =IFERROR((SUMIF(MANOA!$G$7:$G$25,"Terminé",MANOA!$F$7:$F$25)+0.5*SUMIF(MANOA!$G$7:$G$25,"En cours",MANOA!$F$7:$F$25))/SUM(MANOA!$F$7:$F$25),0) -> 1 | F13: =SUM(MANOA!$F$7:$F$25)/60 -> 14 | G13: =(SUMIF(MANOA!$G$7:$G$25,"Terminé",MANOA!$F$7:$F$25)+0.5*SUMIF(MANOA!$G$7:$G$25,"En cours",MANOA!$F$7:$F$25))/60 -> 14 | H13: =(SUMIF(MANOA!$G$7:$G$25,"Pas fini",MANOA!$F$7:$F$25)+0.5*SUMIF(MANOA!$G$7:$G$25,"En cours",MANOA!$F$7:$F$25))/60 -> 0
A14: NOAH — (noahtown011) | B14: Binôme 4 (avec Manoa) | C14: Dashboard + Alertes reproduction + (suite) Ingrédients | D14: =COUNTIF(NOAH!$G$7:$G$24,"Terminé")&"/"&COUNT(NOAH!$A$7:$A$24) -> 18/18 | E14: =IFERROR((SUMIF(NOAH!$G$7:$G$24,"Terminé",NOAH!$F$7:$F$24)+0.5*SUMIF(NOAH!$G$7:$G$24,"En cours",NOAH!$F$7:$F$24))/SUM(NOAH!$F$7:$F$24),0) -> 1 | F14: =SUM(NOAH!$F$7:$F$24)/60 -> 17 | G14: =(SUMIF(NOAH!$G$7:$G$24,"Terminé",NOAH!$F$7:$F$24)+0.5*SUMIF(NOAH!$G$7:$G$24,"En cours",NOAH!$F$7:$F$24))/60 -> 17 | H14: =(SUMIF(NOAH!$G$7:$G$24,"Pas fini",NOAH!$F$7:$F$24)+0.5*SUMIF(NOAH!$G$7:$G$24,"En cours",NOAH!$F$7:$F$24))/60 -> 0
A15: MANDRESY — Mandresy Ally | B15: Renfort santé / transversal | C15: (suite) Catégories de dépenses + modèles finance + renfort module Santé | D15: =COUNTIF(MANDRESY!$G$8:$G$16,"Terminé")&"/"&COUNT(MANDRESY!$A$8:$A$16) -> 9/9 | E15: =IFERROR((SUMIF(MANDRESY!$G$8:$G$16,"Terminé",MANDRESY!$F$8:$F$16)+0.5*SUMIF(MANDRESY!$G$8:$G$16,"En cours",MANDRESY!$F$8:$F$16))/SUM(MANDRESY!$F$8:$F$16),0) -> 1 | F15: =SUM(MANDRESY!$F$8:$F$16)/60 -> 8.25 | G15: =(SUMIF(MANDRESY!$G$8:$G$16,"Terminé",MANDRESY!$F$8:$F$16)+0.5*SUMIF(MANDRESY!$G$8:$G$16,"En cours",MANDRESY!$F$8:$F$16))/60 -> 8.25 | H15: =(SUMIF(MANDRESY!$G$8:$G$16,"Pas fini",MANDRESY!$F$8:$F$16)+0.5*SUMIF(MANDRESY!$G$8:$G$16,"En cours",MANDRESY!$F$8:$F$16))/60 -> 0
A18: Barème dynamique : « Heures faites » = Terminé + ½ En cours ; « Heures restantes » = Pas fini + ½ En cours. L’avancement est calculé sur la durée estimée, pas seulement sur le nombre de fonctions.

Sheet MIARO
A1: MIARO — RAJAONSON Ny Andry Miaro
A2: Binôme 1 (avec Davida) · Branche(s) : dev---Miaro, dev-Miaro-Davida
A3: Socle technique & intégration (fichiers communs) + (suite) Dépenses
A4: ="Avancement : "&COUNTIF($G$7:$G$24,"Terminé")&"/"&COUNT($A$7:$A$24)&" fonctions · "&TEXT(IFERROR((SUMIF($G$7:$G$24,"Terminé",$F$7:$F$24)+0.5*SUMIF($G$7:$G$24,"En cours",$F$7:$F$24))/SUM($F$7:$F$24),0),"0%")&" · Durée totale estimée : "&TEXT(SUM($F$7:$F$24)/60,"0.0")&" h"&" · Heures faites : "&TEXT((SUMIF($G$7:$G$24,"Terminé",$F$7:$F$24)+0.5*SUMIF($G$7:$G$24,"En cours",$F$7:$F$24))/60,"0.0")&" h"&" · Heures restantes : "&TEXT((SUMIF($G$7:$G$24,"Pas fini",$F$7:$F$24)+0.5*SUMIF($G$7:$G$24,"En cours",$F$7:$F$24))/60,"0.0")&" h" -> Avancement : 18/18 fonctions · 100% · Durée totale estimée : 7,3 h · Heures faites : 7,3 h · Heures restantes : 0,0 h
A6: N° | B6: Partie | C6: Couche | D6: Fichier | E6: Fonction / Route (signature) | F6: Durée (min) | G6: Statut | H6: Remarque
A7: 1 | B7: 1ère part | C7: Projet | D7: pom.xml | E7: Configuration Maven + dépendances | F7: 20 | G7: Terminé
A8: 2 | B8: 1ère part | C8: Projet | D8: MadaporcApplication.java | E8: Classe principale Spring Boot | F8: 20 | G8: Terminé
A9: 3 | B9: 1ère part | C9: Config | D9: application.properties | E9: Datasource PostgreSQL + vues JSP + encodage | F9: 15 | G9: Terminé
A10: 4 | B10: 1ère part | C10: Common | D10: common/AppConstants.java | E10: Constantes globales | F10: 10 | G10: Terminé
A11: 5 | B11: 1ère part | C11: BD | D11: resources/schema.sql | E11: Création des tables | F11: 25 | G11: Terminé
A12: 6 | B12: 1ère part | C12: BD | D12: resources/data.sql | E12: Données de test | F12: 25 | G12: Terminé
A13: 7 | B13: 1ère part | C13: CSS | D13: static/css/app.css | E13: Feuille de style | F13: 20 | G13: Terminé
A14: 8 | B14: 1ère part | C14: Vue | D14: layout/header.jsp | E14: En-tête | F14: 20 | G14: Terminé
A15: 9 | B15: 1ère part | C15: Vue | D15: layout/sidebar.jsp | E15: Menu latéral | F15: 20 | G15: Terminé
A16: 10 | B16: 1ère part | C16: Vue | D16: layout/footer.jsp | E16: Pied de page | F16: 20 | G16: Terminé
A17: 11 | B17: 1ère part | C17: Vue | D17: login.jsp · placeholder.jsp | E17: Pages globales | F17: 40 | G17: Terminé
A18: 12 | B18: Suite | C18: Controller | D18: controller/DepenseController.java | E18: @GetMapping(/depenses) listDepenses(Model) | F18: 30 | G18: Terminé
... A24: 18 | B24: Suite | C24: Vue | D24: finance/depenses.jsp · finance/formDepense.jsp | E24: Liste + formulaire dépenses | F24: 40 | G24: Terminé
E25: TOTAL (min) | F25: =SUM($F$7:$F$24) -> 440

Sheet DAVIDA
A1: Dav
A2: Binôme 1 (avec Miaro) · Branche(s) : dev_davida, dev-Miaro-Davida
A3: Authentification & utilisateurs + (suite) Clients
A4: ="Avancement : "&COUNTIF($G$7:$G$29,"Terminé")&"/"&COUNT($A$7:$A$29)&" fonctions · "&TEXT(IFERROR((SUMIF($G$7:$G$29,"Terminé",$F$7:$F$29)+0.5*SUMIF($G$7:$G$29,"En cours",$F$7:$F$29))/SUM($F$7:$F$29),0),"0%")&" · Durée totale estimée : "&TEXT(SUM($F$7:$F$29)/60,"0.0")&" h"&" · Heures faites : "&TEXT((SUMIF($G$7:$G$29,"Terminé",$F$7:$F$29)+0.5*SUMIF($G$7:$G$29,"En cours",$F$7:$F$29))/60,"0.0")&" h"&" · Heures restantes : "&TEXT((SUMIF($G$7:$G$29,"Pas fini",$F$7:$F$29)+0.5*SUMIF($G$7:$G$29,"En cours",$F$7:$F$29))/60,"0.0")&" h" -> Avancement : 23/23 fonctions · 100% · Durée totale estimée : 16,6 h · Heures faites : 16,6 h · Heures restantes : 0,0 h
A6: N° | B6: Partie | C6: Couche | D6: Fichier | E6: Fonction / Route (signature) | F6: Durée (min) | G6: Statut | H6: Remarque
A7: 1 | B7: 1ère part | C7: Controller | D7: controller/AuthController.java | E7: @GetMapping(/login) showLogin(Model) | F7: 30 | G7: Terminé
A8: 2 | B8: 1ère part | C8: Controller | D8: controller/AuthController.java | E8: @PostMapping(/login) login(LoginDTO, Model, HttpSession) | F8: 30 | G8: Terminé
A9: 3 | B9: 1ère part | C9: Controller | D9: controller/AuthController.java | E9: @GetMapping(/logout) logout(HttpSession) | F9: 30 | G9: Terminé
A10: 4 | B10: 1ère part | C10: Controller | D10: controller/UtilisateurController.java | E10: @GetMapping(/utilisateurs) listUtilisateurs(Model) | F10: 30 | G10: Terminé
A11: 5 | B11: 1ère part | C11: Controller | D11: controller/UtilisateurController.java | E11: @GetMapping(/utilisateurs/form) showForm(id, Model) | F11: 30 | G11: Terminé
A12: 6 | B12: 1ère part | C12: Controller | D12: controller/UtilisateurController.java | E12: @PostMapping(/utilisateurs/save) save(UtilisateurDTO, Model) | F12: 30 | G12: Terminé
A13: 7 | B13: 1ère part | C13: Controller | D13: controller/UtilisateurController.java | E13: @PostMapping(/utilisateurs/desactiver/{id}) desactiver(id) | F13: 30 | G13: Terminé
A14: 8 | B14: 1ère part | C14: Service | D14: service/AuthService.java | E14: connecter(LoginDTO, HttpSession) | F14: 30 | G14: Terminé
A15: 9 | B15: 1ère part | C15: Service | D15: service/AuthService.java | E15: verifierMotDePasse(brut, hash) | F15: 30 | G15: Terminé
A16: 10 | B16: 1ère part | C16: Service | D16: service/AuthService.java | E16: deconnecter(HttpSession) | F16: 30 | G16: Terminé
A17: 11 | B17: 1ère part | C17: Service | D17: service/UtilisateurService.java | E17: findAll() · findById(id) · creer(dto) · modifier(id,dto) · desactiver(id) · emailExiste(email) | F17: 180 | G17: Terminé
A18: 12 | B18: 1ère part | C18: Repository | D18: repository/UtilisateurRepository.java | E18: findByEmail(email) · existsByEmail(email) | F18: 30 | G18: Terminé
... A23: 17 | B23: Suite | C23: Controller | D23: controller/ClientController.java | E23: @PostMapping(/clients/save) saveClient(ClientDTO, Model) | F23: 30 | G23: Terminé
A24: 18 | B24: Suite | C24: Controller | D24: controller/ClientController.java | E24: @GetMapping(/clients/{id}) detailClient(id, Model) | F24: 30 | G24: Terminé | H24: Petit probleme de lien mais déjà reglé
A25: 19 | B25: Suite | C25: Service | D25: service/ClientService.java | E25: findAll · findById · creer · modifier · getForm | F25: 150 | G25: Terminé
A26: 20 | B26: Suite | C26: Repository | D26: repository/ClientRepository.java | E26: findAllByOrderByNomAsc · existsByNomIgnoreCase | F26: 30 | G26: Terminé
A27: 21 | B27: Suite | C27: Model | D27: model/Client.java | E27: Entité Client | F27: 15 | G27: Terminé
A28: 22 | B28: Suite | C28: DTO | D28: dto/ClientDTO.java | E28: DTO Client | F28: 10 | G28: Terminé
A29: 23 | B29: Suite | C29: Vue | D29: commerce/clients.jsp · commerce/formClient.jsp | E29: Liste + formulaire clients | F29: 40 | G29: Terminé
E30: TOTAL (min) | F30: =SUM($F$7:$F$29) -> 995

Sheet FANILO
A1: y
A2: Binôme 2 (avec Nomena) · Branche(s) : dev_fanilo, dev_fanilo_nomena
A3: Lots de porcs + mouvements d'effectif + (suite) Ventes
A4: ="Avancement : "&COUNTIF($G$7:$G$26,"Terminé")&"/"&COUNT($A$7:$A$26)&" fonctions · "&TEXT(IFERROR((SUMIF($G$7:$G$26,"Terminé",$F$7:$F$26)+0.5*SUMIF($G$7:$G$26,"En cours",$F$7:$F$26))/SUM($F$7:$F$26),0),"0%")&" · Durée totale estimée : "&TEXT(SUM($F$7:$F$26)/60,"0.0")&" h"&" · Heures faites : "&TEXT((SUMIF($G$7:$G$26,"Terminé",$F$7:$F$26)+0.5*SUMIF($G$7:$G$26,"En cours",$F$7:$F$26))/60,"0.0")&" h"&" · Heures restantes : "&TEXT((SUMIF($G$7:$G$26,"Pas fini",$F$7:$F$26)+0.5*SUMIF($G$7:$G$26,"En cours",$F$7:$F$26))/60,"0.0")&" h" -> Avancement : 20/20 fonctions · 100% · Durée totale estimée : 23,3 h · Heures faites : 23,3 h · Heures restantes : 0,0 h
A6: N° | B6: Partie | C6: Couche | D6: Fichier | E6: Fonction / Route (signature) | F6: Durée (min) | G6: Statut | H6: Remarque
A7: 1 | B7: 1ère part | C7: Controller | D7: controller/LotPorcController.java | E7: @GetMapping(/lots) listLots(LotFiltreDTO, Model) | F7: 30 | G7: Terminé
A8: 2 | B8: 1ère part | C8: Controller | D8: controller/LotPorcController.java | E8: @GetMapping(/lots/form) showForm(id, Model) | F8: 30 | G8: Terminé
A9: 3 | B9: 1ère part | C9: Controller | D9: controller/LotPorcController.java | E9: @PostMapping(/lots/save) save(LotPorcDTO, Model) | F9: 30 | G9: Terminé
A10: 4 | B10: 1ère part | C10: Controller | D10: controller/LotPorcController.java | E10: @GetMapping(/lots/{id}) detail(id, Model) | F10: 30 | G10: Terminé
A11: 5 | B11: 1ère part | C11: Controller | D11: controller/LotPorcController.java | E11: @PostMapping(/lots/archive/{id}) archiver(id) | F11: 30 | G11: Terminé
A12: 6 | B12: 1ère part | C12: Service | D12: service/LotPorcService.java | E12: rechercherLots(filtre) · prepareFormModel · creerLot · modifierLot · getDetailLot · archiverLot · existeCodeLot · verifierLotActif | F12: 240 | G12: Terminé
A13: 7 | B13: 1ère part | C13: Repository | D13: repository/LotPorcRepository.java | E13: existsByCodeLot · findByCodeLotContainingIgnoreCase · findBySexe · findByObjectif · findByStatut · countByStatut | F13: 90 | G13: Terminé
A14: 8 | B14: 1ère part | C14: Model/DTO | D14: model/LotPorc.java · Race.java · dto/LotPorcDTO.java · LotFiltreDTO.java · LotDetailDTO.java | E14: Entités + DTO lots | F14: 75 | G14: Terminé
A15: 9 | B15: 1ère part | C15: Vue | D15: lots/listeLots.jsp · formLot.jsp · detailLot.jsp | E15: Vues lots | F15: 60 | G15: Terminé
A16: 10 | B16: 1ère part | C16: Controller | D16: controller/MouvementLotController.java | E16: @GetMapping(/lots/{id}/mouvements) listMouvements(id, Model) | F16: 30 | G16: Terminé
A17: 11 | B17: 1ère part | C17: Controller | D17: controller/MouvementLotController.java | E17: @PostMapping(/lots/mouvements/save) saveMouvement(MouvementLotDTO, Model) | F17: 30 | G17: Terminé
A18: 12 | B18: 1ère part | C18: Service | D18: service/MouvementLotService.java | E18: getMouvementsByLot · enregistrerMouvement · augmenterEffectif · diminuerEffectif · verifierQuantiteDisponible | F18: 150 | G18: Terminé
... A20: 14 | B20: 1ère part | C20: Model/DTO/Vue | D20: model/MouvementLotPorc.java · dto/MouvementLotDTO.java · lots/mouvements.jsp | E20: Mouvements d'effectif | F20: 45 | G20: Terminé
A21: 15 | B21: Suite | C21: Controller | D21: controller/VenteController.java | E21: listVentes · showForm · save · valider(/ventes/valider/{id}) · annuler · genererRecuPdf | F21: 180 | G21: Terminé | H21: FICHIER VIDE (0 ligne)
A22: 16 | B22: Suite | C22: Service | D22: service/VenteService.java | E22: findAll · creerVente · validerVente · annulerVente · calculerMontantTotal · genererRecuPdf | F22: 180 | G22: Terminé | H22: FICHIER VIDE (0 ligne)
A23: 17 | B23: Suite | C23: Repository | D23: repository/VenteRepository.java · DetailVenteRepository.java | E23: byDateVente · byStatut · byVenteId | F23: 45 | G23: Terminé | H23: Présent (23 lignes)
A24: 18 | B24: Suite | C24: Model | D24: model/Vente.java · DetailVente.java | E24: Entités (statuts BROUILLON/VALIDEE/ANNULEE) | F24: 30 | G24: Terminé | H24: Présent (48 lignes)
A25: 19 | B25: Suite | C25: DTO | D25: dto/VenteDTO.java · DetailVenteDTO.java | E25: DTO ventes | F25: 20 | G25: Terminé | H25: À vérifier
A26: 20 | B26: Suite | C26: Vue | D26: commerce/ventes.jsp · formVente.jsp · detailVente.jsp | E26: Vues ventes | F26: 60 | G26: Terminé
E27: TOTAL (min) | F27: =SUM($F$7:$F$26) -> 1400

Sheet NOMENA
A1: NOMENA — Andriantsiferana Sarobidy
A2: Binôme 2 (avec Fanilo) · Branche(s) : dev_Nomena, dev_fanilo_nomena
A3: Pesées des lots + Santé (pas de part dans la suite)
A4: ="Avancement : "&COUNTIF($G$7:$G$19,"Terminé")&"/"&COUNT($A$7:$A$19)&" fonctions · "&TEXT(IFERROR((SUMIF($G$7:$G$19,"Terminé",$F$7:$F$19)+0.5*SUMIF($G$7:$G$19,"En cours",$F$7:$F$19))/SUM($F$7:$F$19),0),"0%")&" · Durée totale estimée : "&TEXT(SUM($F$7:$F$19)/60,"0.0")&" h"&" · Heures faites : "&TEXT((SUMIF($G$7:$G$19,"Terminé",$F$7:$F$19)+0.5*SUMIF($G$7:$G$19,"En cours",$F$7:$F$19))/60,"0.0")&" h"&" · Heures restantes : "&TEXT((SUMIF($G$7:$G$19,"Pas fini",$F$7:$F$19)+0.5*SUMIF($G$7:$G$19,"En cours",$F$7:$F$19))/60,"0.0")&" h" -> Avancement : 13/13 fonctions · 100% · Durée totale estimée : 12,5 h · Heures faites : 12,5 h · Heures restantes : 0,0 h
A6: N° | B6: Partie | C6: Couche | D6: Fichier | E6: Fonction / Route (signature) | F6: Durée (min) | G6: Statut | H6: Remarque
A7: 1 | B7: 1ère part | C7: Controller | D7: controller/PeseeLotController.java | E7: @GetMapping(/lots/{id}/pesees) listPesees(id, Model) | F7: 30 | G7: Terminé
A8: 2 | B8: 1ère part | C8: Controller | D8: controller/PeseeLotController.java | E8: @PostMapping(/lots/pesees/save) savePesee(PeseeLotDTO, Model) | F8: 30 | G8: Terminé
A9: 3 | B9: 1ère part | C9: Service | D9: service/PeseeLotService.java | E9: getPeseesByLot(lotId) · enregistrerPesee(dto) · calculerEvolutionPoids(lotId) | F9: 90 | G9: Terminé
A10: 4 | B10: 1ère part | C10: Repository | D10: repository/PeseeLotRepository.java | E10: findByLotIdOrderByDatePeseeAsc(lotId) | F10: 15 | G10: Terminé
A11: 5 | B11: 1ère part | C11: Model/DTO/Vue | D11: model/PeseeLot.java · dto/PeseeLotDTO.java · lots/pesees.jsp | E11: Pesées | F11: 45 | G11: Terminé
A12: 6 | B12: 1ère part | C12: Controller | D12: controller/VaccinController.java | E12: /vaccins · /vaccins/form · /vaccins/save | F12: 90 | G12: Terminé
A13: 7 | B13: 1ère part | C13: Controller | D13: controller/VaccinationController.java | E13: /vaccinations · /vaccinations/form · /vaccinations/save | F13: 90 | G13: Terminé
A14: 8 | B14: 1ère part | C14: Controller | D14: controller/SuiviSanitaireController.java | E14: /sante/suivis · /sante/suivis/form · /sante/suivis/save | F14: 90 | G14: Terminé
A15: 9 | B15: 1ère part | C15: Service | D15: service/VaccinService.java · VaccinationService.java · SuiviSanitaireService.java | E15: Logique métier vaccins / vaccinations / suivis | F15: 30 | G15: Terminé
A16: 10 | B16: 1ère part | C16: Repository | D16: Vaccin · Vaccination · Maladie · Traitement · SuiviSanitaire Repository | E16: Accès données santé | F16: 15 | G16: Terminé
A17: 11 | B17: 1ère part | C17: Model | D17: Vaccin · Vaccination · Maladie · Traitement · SuiviSanitaire | E17: Entités santé | F17: 75 | G17: Terminé
A18: 12 | B18: 1ère part | C18: DTO | D18: VaccinDTO · VaccinationDTO · SuiviSanitaireDTO | E18: DTO santé | F18: 30 | G18: Terminé
A19: 13 | B19: 1ère part | C19: Vue | D19: sante/vaccins · formVaccin · vaccinations · formVaccination · suivis · formSuivi | E19: Vues santé | F19: 120 | G19: Terminé
E20: TOTAL (min) | F20: =SUM($F$7:$F$19) -> 750

Sheet TSANTA
A1: TSANTA — Tsanta Finaritra (Noahmathieu)
A2: Binôme 3 (avec Mickaella) · Branche(s) : dev_Tsanta, dev_TsantaSuite
A3: Création & suivi initial du groupe de reproduction + (suite) Import / Export
A4: ="Avancement : "&COUNTIF($G$7:$G$24,"Terminé")&"/"&COUNT($A$7:$A$24)&" fonctions · "&TEXT(IFERROR((SUMIF($G$7:$G$24,"Terminé",$F$7:$F$24)+0.5*SUMIF($G$7:$G$24,"En cours",$F$7:$F$24))/SUM($F$7:$F$24),0),"0%")&" · Durée totale estimée : "&TEXT(SUM($F$7:$F$24)/60,"0.0")&" h"&" · Heures faites : "&TEXT((SUMIF($G$7:$G$24,"Terminé",$F$7:$F$24)+0.5*SUMIF($G$7:$G$24,"En cours",$F$7:$F$24))/60,"0.0")&" h"&" · Heures restantes : "&TEXT((SUMIF($G$7:$G$24,"Pas fini",$F$7:$F$24)+0.5*SUMIF($G$7:$G$24,"En cours",$F$7:$F$24))/60,"0.0")&" h" -> Avancement : 18/18 fonctions · 100% · Durée totale estimée : 16,5 h · Heures faites : 16,5 h · Heures restantes : 0,0 h
A6: N° | B6: Partie | C6: Couche | D6: Fichier | E6: Fonction / Route (signature) | F6: Durée (min) | G6: Statut | H6: Remarque
A7: 1 | B7: 1ère part | C7: Controller | D7: controller/GroupeReproductionController.java | E7: @GetMapping(/reproduction/groupes) listGroupes(Model) | F7: 30 | G7: Terminé
A8: 2 | B8: 1ère part | C8: Controller | D8: controller/GroupeReproductionController.java | E8: @GetMapping(/reproduction/groupes/form) showForm(id, Model) | F8: 30 | G8: Terminé
A9: 3 | B9: 1ère part | C9: Controller | D9: controller/GroupeReproductionController.java | E9: @PostMapping(/reproduction/groupes/save) save(dto, Model, HttpSession) | F9: 30 | G9: Terminé
A10: 4 | B10: 1ère part | C10: Service | D10: service/GroupeReproductionCreationService.java | E10: creer(dto, utilisateurId) | F10: 30 | G10: Terminé
A11: 5 | B11: 1ère part | C11: Service | D11: service/GroupeReproductionCreationService.java | E11: modifier(id, dto) | F11: 30 | G11: Terminé
A12: 6 | B12: 1ère part | C12: Service | D12: service/GroupeReproductionCreationService.java | E12: calculerDatePrevueMiseBas(dateSaillie, dureeGestation) | F12: 30 | G12: Terminé
A13: 7 | B13: 1ère part | C13: Service | D13: service/GroupeReproductionCreationService.java | E13: verifierLotFemelle · verifierLotMale · verifierFemellesDisponibles | F13: 90 | G13: Terminé
A14: 8 | B14: 1ère part | C14: Service | D14: service/GroupeReproductionCreationService.java | E14: mettreAJourRepartitionApresSaillie(lotId, nombreFemelles) | F14: 30 | G14: Terminé
A15: 9 | B15: 1ère part | C15: Service | D15: service/GroupeReproductionQueryService.java | E15: findAll() · getDetailGroupe(id) · prepareFormModel(Model, id) | F15: 90 | G15: Terminé
A16: 10 | B16: 1ère part | C16: Repository | D16: repository/GroupeReproductionRepository.java | E16: findAllByOrderByDateSaillieDesc · findByLotFemelleId · countByStatutIn | F16: 45 | G16: Terminé
A17: 11 | B17: 1ère part | C17: Repository | D17: repository/ParametreReproductionRaceRepository.java | E17: findByRaceId(raceId) | F17: 15 | G17: Terminé
A18: 12 | B18: 1ère part | C18: Model/DTO/Vue | D18: model/GroupeReproduction.java · ParametreReproductionRace.java · dto/GroupeReproductionDTO.java · GroupeReproductionDetailDTO.java · groupes/liste.jsp · form.jsp | E18: Entités + DTO + vues création | F18: 90 | G18: Terminé
... A24: 18 | B24: Suite | C24: Vue | D24: imports/form.jsp · imports/historique.jsp | E24: Vues import + historique | F24: 40 | G24: Terminé
E25: TOTAL (min) | F25: =SUM($F$7:$F$24) -> 990

Sheet MICKAELLA
A1: MICKAELLA — Andriamarondraibe
A2: Binôme 3 (avec Tsanta) · Branche(s) : feature-binome3
A3: Détail groupe, confirmation mise bas & lot naissance + (suite) Rapports financiers
A4: ="Avancement : "&COUNTIF($G$7:$G$27,"Terminé")&"/"&COUNT($A$7:$A$27)&" fonctions · "&TEXT(IFERROR((SUMIF($G$7:$G$27,"Terminé",$F$7:$F$27)+0.5*SUMIF($G$7:$G$27,"En cours",$F$7:$F$27))/SUM($F$7:$F$27),0),"0%")&" · Durée totale estimée : "&TEXT(SUM($F$7:$F$27)/60,"0.0")&" h"&" · Heures faites : "&TEXT((SUMIF($G$7:$G$27,"Terminé",$F$7:$F$27)+0.5*SUMIF($G$7:$G$27,"En cours",$F$7:$F$27))/60,"0.0")&" h"&" · Heures restantes : "&TEXT((SUMIF($G$7:$G$27,"Pas fini",$F$7:$F$27)+0.5*SUMIF($G$7:$G$27,"En cours",$F$7:$F$27))/60,"0.0")&" h" -> Avancement : 21/21 fonctions · 100% · Durée totale estimée : 12,7 h · Heures faites : 12,7 h · Heures restantes : 0,0 h
A6: N° | B6: Partie | C6: Couche | D6: Fichier | E6: Fonction / Route (signature) | F6: Durée (min) | G6: Statut | H6: Remarque
A7: 1 | B7: 1ère part | C7: Controller | D7: controller/GroupeReproductionController.java | E7: @GetMapping(/reproduction/groupes/{id}) detail(id, Model) | F7: 30 | G7: Terminé
A8: 2 | B8: 1ère part | C8: Controller | D8: controller/GroupeReproductionController.java | E8: @GetMapping(/{id}/confirmer-mise-bas) afficherFormulaireMiseBas(id, Model) | F8: 30 | G8: Terminé | H8: =#ERR520! -> #N/A
A9: 3 | B9: 1ère part | C9: Controller | D9: controller/GroupeReproductionController.java | E9: @PostMapping(/{id}/confirmer-mise-bas) confirmerMiseBas(id, dto, Model) | F9: 30 | G9: Terminé
A10: 4 | B10: 1ère part | C10: Controller | D10: controller/GroupeReproductionController.java | E10: @PostMapping(/{id}/cloturer) cloturer(id) | F10: 30 | G10: Terminé | H10: Implémentée
A11: 5 | B11: 1ère part | C11: Service | D11: service/GroupeReproductionMiseBasService.java | E11: getDetailGroupe(groupeId) | F11: 30 | G11: Terminé
A12: 6 | B12: 1ère part | C12: Service | D12: service/GroupeReproductionMiseBasService.java | E12: calculerJoursRestants(groupeId) | F12: 30 | G12: Terminé
A13: 7 | B13: 1ère part | C13: Service | D13: service/GroupeReproductionMiseBasService.java | E13: calculerPourcentageEvolution(groupeId) | F13: 30 | G13: Terminé
A14: 8 | B14: 1ère part | C14: Service | D14: service/GroupeReproductionMiseBasService.java | E14: confirmerMiseBas(groupeId, dto) | F14: 30 | G14: Terminé
A15: 9 | B15: 1ère part | C15: Service | D15: service/GroupeReproductionMiseBasService.java | E15: validerDonneesMiseBas(dto) | F15: 30 | G15: Terminé | H15: Présente
A16: 10 | B16: 1ère part | C16: Service | D16: service/GroupeReproductionMiseBasService.java | E16: mettreAJourGroupeApresMiseBas(groupeId, dto) | F16: 30 | G16: Terminé | H16: Présente
A17: 11 | B17: 1ère part | C17: Service | D17: service/GroupeReproductionMiseBasService.java | E17: mettreAJourRepartitionApresMiseBas(lotId, groupe) | F17: 30 | G17: Terminé | H17: Via repartitionReproductiveService.mettreAJourApresMiseBas
A18: 12 | B18: 1ère part | C18: Service | D18: service/GroupeReproductionMiseBasService.java | E18: cloturer(groupeId) | F18: 30 | G18: Terminé | H18: Implémentée
A19: 13 | B19: 1ère part | C19: Service | D19: service/LotNaissanceService.java | E19: creerLotNaissanceApresMiseBas(groupeId, dto) | F19: 30 | G19: Terminé | H19: Implémentée (création lot + lien lot mère/groupe)
A20: 14 | B20: 1ère part | C20: Service | D20: service/LotNaissanceService.java | E20: preparerLotNaissanceDepuisGroupe(groupeId) | F20: 30 | G20: Terminé | H20: Implémentée
A21: 15 | B21: 1ère part | C21: DTO | D21: dto/ConfirmationMiseBasDTO.java · LotNaissanceDTO.java | E21: DTO mise bas + lot naissance | F21: 20 | G21: Terminé
A22: 16 | B22: 1ère part | C22: Vue | D22: reproduction/groupes/detail.jsp · confirmerMiseBas.jsp | E22: Détail groupe + barre évolution + confirmation | F22: 40 | G22: Terminé
A23: 17 | B23: Suite | C23: Controller | D23: controller/RapportController.java | E23: @GetMapping(/rapports) index(RapportFiltreDTO, Model) | F23: 30 | G23: Terminé | H23: Implémenté (bilan financier filtré par dates)
A24: 18 | B24: Suite | C24: Service | D24: service/RapportService.java | E24: genererRapport · calculerTotalVentes (VALIDEE) · calculerTotalDepenses · calculerBeneficeNet · compterVentes · compterDepenses · validerFiltre | F24: 210 | G24: Terminé | H24: Implémenté
A25: 19 | B25: Suite | C25: DTO | D25: dto/RapportFiltreDTO.java | E25: Filtre dates rapport (dateDebut, dateFin) | F25: 10 | G25: Terminé | H25: Complété
A26: 20 | B26: Suite | C26: DTO | D26: dto/RapportFinancierDTO.java | E26: totalVentes · totalDepenses · beneficeNet · nbVentes · nbDepenses | F26: 10 | G26: Terminé | H26: Créé
A27: 21 | B27: Suite | C27: Vue | D27: rapports/index.jsp | E27: Bilan financier + filtre dates | F27: 20 | G27: Terminé | H27: Bloc financier ajouté
E28: TOTAL (min) | F28: =SUM($F$7:$F$27) -> 760

Sheet MANOA
A1: MANOA — Aina Manoa Rajoel
A2: Binôme 4 (avec Noah) · Branche(s) : dev-Manoa
A3: Analyse reproductive & formules métier + (suite) Mouvements de stock alimentaire
A4: ="Avancement : "&COUNTIF($G$7:$G$25,"Terminé")&"/"&COUNT($A$7:$A$25)&" fonctions · "&TEXT(IFERROR((SUMIF($G$7:$G$25,"Terminé",$F$7:$F$25)+0.5*SUMIF($G$7:$G$25,"En cours",$F$7:$F$25))/SUM($F$7:$F$25),0),"0%")&" · Durée totale estimée : "&TEXT(SUM($F$7:$F$25)/60,"0.0")&" h"&" · Heures faites : "&TEXT((SUMIF($G$7:$G$25,"Terminé",$F$7:$F$25)+0.5*SUMIF($G$7:$G$25,"En cours",$F$7:$F$25))/60,"0.0")&" h"&" · Heures restantes : "&TEXT((SUMIF($G$7:$G$25,"Pas fini",$F$7:$F$25)+0.5*SUMIF($G$7:$G$25,"En cours",$F$7:$F$25))/60,"0.0")&" h" -> Avancement : 19/19 fonctions · 100% · Durée totale estimée : 14,0 h · Heures faites : 14,0 h · Heures restantes : 0,0 h
A6: N° | B6: Partie | C6: Couche | D6: Fichier | E6: Fonction / Route (signature) | F6: Durée (min) | G6: Statut | H6: Remarque
A7: 1 | B7: 1ère part | C7: Controller | D7: controller/AnalyseReproductionController.java | E7: @GetMapping(/reproduction/analyse/lots/{lotId}) analyseLot(lotId, Model) | F7: 30 | G7: Terminé
A8: 2 | B8: 1ère part | C8: Controller | D8: controller/AnalyseReproductionController.java | E8: @PostMapping(/reproduction/analyse/generer/{lotId}) genererAnalyse(lotId, Model) | F8: 30 | G8: Terminé
A9: 3 | B9: 1ère part | C9: Service | D9: service/AnalyseReproductionService.java | E9: analyserLot(lotId) | F9: 30 | G9: Terminé
A10: 4 | B10: 1ère part | C10: Service | D10: service/AnalyseReproductionService.java | E10: calculerTauxAptitudeGlobal(dto) · calculerTauxRecommande(dto) · calculerTauxFertiliteObserve(dto) | F10: 90 | G10: Terminé
A11: 5 | B11: 1ère part | C11: Service | D11: service/AnalyseReproductionService.java | E11: genererDecision(dto) · enregistrerAnalyse(dto) | F11: 60 | G11: Terminé
A12: 6 | B12: 1ère part | C12: Service | D12: service/RepartitionReproductiveService.java | E12: initialiserRepartitionLotFemelle(lotId) · getRepartitionByLot(lotId) | F12: 60 | G12: Terminé
A13: 7 | B13: 1ère part | C13: Service | D13: service/RepartitionReproductiveService.java | E13: calculerFemellesDisponibles(lotId) | F13: 30 | G13: Terminé | H13: Terminé (refactorisé) : logique dans initialiserRepartitionLotFemelle / getQuantite
A14: 8 | B14: 1ère part | C14: Service | D14: service/RepartitionReproductiveService.java | E14: calculerFemellesEnCycle(lotId) | F14: 30 | G14: Terminé | H14: Terminé (refactorisé) : getQuantite(lotId, "EN_CYCLE")
A15: 9 | B15: 1ère part | C15: Service | D15: service/RepartitionReproductiveService.java | E15: mettreAJourRepartition(lotId, statut, quantite) | F15: 30 | G15: Terminé
A16: 10 | B16: 1ère part | C16: Repository | D16: repository/AnalyseReproductionLotRepository.java | E16: findByLotIdOrderByDateAnalyseDesc(lotId) | F16: 15 | G16: Terminé
A17: 11 | B17: 1ère part | C17: Repository | D17: repository/RepartitionReproductiveLotRepository.java | E17: findByLotId · findByLotIdAndStatutReproductif | F17: 30 | G17: Terminé
A18: 12 | B18: 1ère part | C18: Repository | D18: repository/StatutReproductifRepository.java | E18: findAll() | F18: 15 | G18: Terminé
A19: 13 | B19: 1ère part | C19: Model/DTO/Vue | D19: model/AnalyseReproductionLot.java · RepartitionReproductiveLot.java · StatutReproductif.java · dto/AnalyseReproductionLotDTO.java · RepartitionReproductiveDTO.java · analyse/analyseLot.jsp | E19: Entités + DTO + vue analyse | F19: 90 | G19: Terminé
A20: 14 | B20: Suite | C20: Controller | D20: controller/MouvementStockController.java | E20: listMouvements · showForm · saveMouvement(ingredientId, typeMouvement, quantite, Model) | F20: 90 | G20: Terminé | H20: Présent (46 lignes)
A21: 15 | B21: Suite | C21: Service | D21: service/MouvementStockService.java | E21: enregistrerMouvementStock · verifierStockDisponible | F21: 60 | G21: Terminé | H21: Présent (101 lignes)
A22: 16 | B22: Suite | C22: Service | D22: service/MouvementStockService.java | E22: appliquerEntree · appliquerSortie | F22: 60 | G22: Terminé | H22: Présent : appliquerEntree (l.71) / appliquerSortie (l.80)
A23: 17 | B23: Suite | C23: Repository | D23: repository/MouvementStockAlimentRepository.java | E23: orderByDate · byIngredient | F23: 30 | G23: Terminé | H23: Renommé : MouvementStockRepository.findAllByOrderByIdDesc()
A24: 18 | B24: Suite | C24: Model | D24: model/MouvementStockAliment.java | E24: Entité (ENTREE/SORTIE/AJUSTEMENT) | F24: 15 | G24: Terminé | H24: Renommé : model/MouvementStock.java (le fichier existe)
A25: 19 | B25: Suite | C25: DTO/Vue | D25: dto/MouvementStockDTO.java · stocks/mouvements.jsp · formMouvement.jsp | E25: DTO + vues mouvements stock | F25: 45 | G25: Terminé
E26: TOTAL (min) | F26: =SUM($F$7:$F$25) -> 840

Sheet NOAH
A1: NOAH — (noahtown011)
A2: Binôme 4 (avec Manoa) · Branche(s) : dev-binome-4, dev-binome-Noah, dev-Noah-View
A3: Dashboard + Alertes reproduction + (suite) Ingrédients
A4: ="Avancement : "&COUNTIF($G$7:$G$24,"Terminé")&"/"&COUNT($A$7:$A$24)&" fonctions · "&TEXT(IFERROR((SUMIF($G$7:$G$24,"Terminé",$F$7:$F$24)+0.5*SUMIF($G$7:$G$24,"En cours",$F$7:$F$24))/SUM($F$7:$F$24),0),"0%")&" · Durée totale estimée : "&TEXT(SUM($F$7:$F$24)/60,"0.0")&" h"&" · Heures faites : "&TEXT((SUMIF($G$7:$G$24,"Terminé",$F$7:$F$24)+0.5*SUMIF($G$7:$G$24,"En cours",$F$7:$F$24))/60,"0.0")&" h"&" · Heures restantes : "&TEXT((SUMIF($G$7:$G$24,"Pas fini",$F$7:$F$24)+0.5*SUMIF($G$7:$G$24,"En cours",$F$7:$F$24))/60,"0.0")&" h" -> Avancement : 18/18 fonctions · 100% · Durée totale estimée : 17,0 h · Heures faites : 17,0 h · Heures restantes : 0,0 h
A6: N° | B6: Partie | C6: Couche | D6: Fichier | E6: Fonction / Route (signature) | F6: Durée (min) | G6: Statut | H6: Remarque
A7: 1 | B7: 1ère part | C7: Controller | D7: controller/DashboardController.java | E7: @GetMapping(/dashboard) dashboard(Model, HttpSession) | F7: 30 | G7: Terminé
A8: 2 | B8: 1ère part | C8: Service | D8: service/DashboardService.java | E8: getDashboard(debut, fin) | F8: 30 | G8: Terminé
A9: 3 | B9: 1ère part | C9: Service | D9: service/DashboardService.java | E9: compterLotsActifs · calculerTotalPorcsActifs · compterGroupesReproductionActifs · compterMisesBasProches | F9: 120 | G9: Terminé
A10: 4 | B10: 1ère part | C10: Service | D10: service/DashboardService.java | E10: calculerTauxAptitudeGlobal · calculerTauxFertiliteGlobal | F10: 60 | G10: Terminé
A11: 5 | B11: 1ère part | C11: Service | D11: service/DashboardService.java | E11: calculerVentesMois · calculerDepensesMois · calculerBeneficeNet | F11: 90 | G11: Terminé
A12: 6 | B12: 1ère part | C12: Service | D12: service/DashboardService.java | E12: listerStocksFaibles · listerVaccinationsAVenir(dateLimite) | F12: 60 | G12: Terminé
A13: 7 | B13: 1ère part | C13: DTO | D13: dto/DashboardDTO.java | E13: DTO indicateurs | F13: 10 | G13: Terminé
A14: 8 | B14: 1ère part | C14: Vue | D14: dashboard/index.jsp | E14: Tableau de bord + graphes | F14: 20 | G14: Terminé | H14: Graphe d'évolution ne montre pas montées/chutes + bouton générer rapport KO (correction.md)
A15: 9 | B15: 1ère part | C15: Controller | D15: controller/AlerteReproductionController.java | E15: @GetMapping(/reproduction/alertes) listAlertes(Model) | F15: 30 | G15: Terminé
A16: 10 | B16: 1ère part | C16: Controller | D16: controller/AlerteReproductionController.java | E16: @PostMapping(/{id}/lire) marquerCommeLue(id) | F16: 30 | G16: Terminé
A17: 11 | B17: 1ère part | C17: Controller | D17: controller/AlerteReproductionController.java | E17: @PostMapping(/{id}/traiter) traiter(id) | F17: 30 | G17: Terminé
A18: 12 | B18: 1ère part | C18: Service | D18: service/AlerteReproductionService.java | E18: listerAlertesActives · genererAlertesMiseBasProche · marquerCommeLue · traiter | F18: 120 | G18: Terminé
A19: 13 | B19: 1ère part | C19: Repository | D19: repository/AlerteReproductionRepository.java | E19: findByStatut · findByTypeAlerteAndStatut | F19: 30 | G19: Terminé
A20: 14 | B20: 1ère part | C20: Model/DTO/Vue | D20: model/AlerteReproduction.java · dto/AlerteReproductionDTO.java · reproduction/alertes/liste.jsp | E20: Entité + DTO + vue alertes | F20: 45 | G20: Terminé
A21: 15 | B21: Suite | C21: Controller | D21: controller/IngredientController.java | E21: listIngredients · showForm · save | F21: 90 | G21: Terminé
A22: 16 | B22: Suite | C22: Service | D22: service/IngredientService.java | E22: findAllIngredients · creerIngredient · modifierIngredient · listerStocksFaibles | F22: 120 | G22: Terminé
A23: 17 | B23: Suite | C23: Repository | D23: repository/IngredientRepository.java | E23: findAllByOrderByNomAsc · existsByNomIgnoreCase · findStocksFaibles | F23: 45 | G23: Terminé
A24: 18 | B24: Suite | C24: Model/DTO/Vue | D24: model/Ingredient.java · dto/IngredientDTO.java · stocks/ingredients.jsp · formIngredient.jsp | E24: Entité + DTO + vues ingrédients | F24: 60 | G24: Terminé
E25: TOTAL (min) | F25: =SUM($F$7:$F$24) -> 1020

Sheet MANDRESY
A1: MANDRESY — Mandresy Ally
A2: Renfort santé / transversal · Branche(s) : dev_mandresy, frontend
A3: (suite) Catégories de dépenses + modèles finance + renfort module Santé
A4: ="Avancement : "&COUNTIF($G$8:$G$16,"Terminé")&"/"&COUNT($A$8:$A$16)&" fonctions · "&TEXT(IFERROR((SUMIF($G$8:$G$16,"Terminé",$F$8:$F$16)+0.5*SUMIF($G$8:$G$16,"En cours",$F$8:$F$16))/SUM($F$8:$F$16),0),"0%")&" · Durée totale estimée : "&TEXT(SUM($F$8:$F$16)/60,"0.0")&" h"&" · Heures faites : "&TEXT((SUMIF($G$8:$G$16,"Terminé",$F$8:$F$16)+0.5*SUMIF($G$8:$G$16,"En cours",$F$8:$F$16))/60,"0.0")&" h"&" · Heures restantes : "&TEXT((SUMIF($G$8:$G$16,"Pas fini",$F$8:$F$16)+0.5*SUMIF($G$8:$G$16,"En cours",$F$8:$F$16))/60,"0.0")&" h" -> Avancement : 9/9 fonctions · 100% · Durée totale estimée : 8,3 h · Heures faites : 8,3 h · Heures restantes : 0,0 h
A7: N° | B7: Partie | C7: Couche | D7: Fichier | E7: Fonction / Route (signature) | F7: Durée (min) | G7: Statut | H7: Remarque
A8: 0 | B8: All Interface | C8: All JSP | F8: 200 | G8: Terminé
A9: 1 | B9: Suite | C9: Model | D9: model/Depense.java | E9: Entité Dépense (categorie, dateDepense, montant, description) | F9: 15 | G9: Terminé
A10: 2 | B10: Suite | C10: Model | D10: model/CategorieDepense.java | E10: Entité CategorieDepense (id, nom) | F10: 15 | G10: Terminé
A11: 3 | B11: Suite | C11: DTO | D11: dto/DepenseDTO.java | E11: DTO Dépense | F11: 10 | G11: Terminé
A12: 4 | B12: Suite | C12: DTO | D12: dto/CategorieDepenseDTO.java | E12: DTO Catégorie | F12: 10 | G12: Terminé
A13: 5 | B13: Suite | C13: Repository | D13: repository/CategorieDepenseRepository.java | E13: findAllByOrderByNomAsc · existsByNomIgnoreCase | F13: 30 | G13: Terminé
A14: 6 | B14: Suite | C14: Service | D14: service/CategorieDepenseService.java | E14: findAllCategories · findById · creer · modifier · valider | F14: 150 | G14: Terminé
A15: 7 | B15: Suite | C15: BD | D15: resources/data.sql | E15: Catégories (Alimentation, Santé, Personnel, Transport, Maintenance, Autre) | F15: 25 | G15: Terminé
A16: 8 | B16: Renfort | C16: Santé | D16: sante/* · layout/sidebar.jsp | E16: Renfort module Santé (vaccin/vaccination/traitement/maladie) + sidebar | F16: 40 | G16: Terminé
E17: TOTAL (min) | F17: =SUM($F$8:$F$16) -> 495

Sheet Transversal & Jury
A1: Tâches transversales — exigences jury & corrections (responsable / toute l'équipe)
A3: ="Durée totale estimée : "&TEXT(SUM($G$5:$G$18)/60,"0.0")&" h"&" · Heures faites : "&TEXT((SUMIF($E$5:$E$18,"Terminé",$G$5:$G$18)+0.5*SUMIF($E$5:$E$18,"En cours",$G$5:$G$18))/60,"0.0")&" h"&" · Heures restantes : "&TEXT((SUMIF($E$5:$E$18,"Pas fini",$G$5:$G$18)+0.5*SUMIF($E$5:$E$18,"En cours",$G$5:$G$18))/60,"0.0")&" h" -> Durée totale estimée : 13,0 h · Heures faites : 2,5 h · Heures restantes : 10,5 h
A4: N° | B4: Catégorie | C4: Tâche / exigence | D4: Fichiers | E4: Statut | F4: Remarque | G4: Durée (min)
A5: 1 | B5: Export | C5: Export Excel : lots / ventes / groupes repro / analyse | D5: service/ImportExportService.java | E5: Pas fini | F5: Service vide — exigence jury | G5: 120
A6: 2 | B6: Export | C6: Rapports PDF : reproduction / commercial / sanitaire / reçu vente | D6: service/RapportService.java | E6: Pas fini | F6: Service vide — exigence jury | G6: 120
A7: 3 | B7: Import | C7: Import Excel : lots / clients / vaccinations / ingrédients (+ doublons & colonnes) | D7: service/ImportExportService.java | E7: Pas fini | F7: Service vide — exigence jury | G7: 120
A8: 4 | B8: Import | C8: Template de fichier de départ pour le client | D8: — | E8: Terminé | G8: 30
A9: 5 | B9: Recherche | C9: Recherche multi-critères sur toutes les listes | D9: tous les controllers/listes | E9: Pas fini | G9: 30
A10: 6 | B10: Recherche | C10: Recherche par intervalle (chiffres & dates) | D10: listes | E10: Pas fini | G10: 30
A11: 7 | B11: Recherche | C11: Recherche par checkbox sur clés étrangères / catégories | D11: listes | E11: Pas fini | G11: 30
A12: 8 | B12: Liste | C12: Pagination côté back / base | D12: listes | E12: Terminé | G12: 30
A13: 9 | B13: Liste | C13: Tri croissant / décroissant | D13: listes | E13: Pas fini | G13: 30
A14: 10 | B14: Dashboard | C14: Graphes : histogramme, courbe, camembert (évolution ventes) | D14: dashboard/index.jsp | E14: Terminé | F14: Évolution mal affichée (correction.md) | G14: 30
A15: 11 | B15: Bug | C15: Bouton « Générer rapport » | D15: dashboard / rapports | E15: Pas fini | F15: Ne marche pas (correction.md) | G15: 30
A16: 12 | B16: Bug | C16: Bouton « Retour au lot » (page mouvements) | D16: lots/mouvements.jsp | E16: Pas fini | F16: Ne marche plus (correction.md) | G16: 30
A17: 13 | B17: Bug | C17: Redirection saisie poids de départ après création lot | D17: lots/pesees.jsp | E17: Pas fini | F17: À implémenter (correction.md) | G17: 30
A18: 14 | B18: Tests | C18: Jeu de données + scénario soutenance (LOT-F-001, LOT-M-001, GR-001, mise bas, LOT-N-001, ventes, exports/imports) | D18: e | E18: En cours | F18: Exigence plan | G18: 120
F19: TOTAL (min) | G19: =SUM($G$5:$G$18) -> 780

Sheet Sheet12
C2: ETU | D2: NB absence | E2: Date absence | F2: cause | G2: point
C3: Tsanta | D3: 2 | E3: 02/07/2026 et 01/07/2026 | F3: Malade | G3: 1
C4: Faniry | D4: Jamais present 0 | E4: 0 | F4: injustifier | G4: -3
C5: Fanilo | D5: 0 | E5: 0 | F5: Toujours présent | G5: 1
C6: Noah | D6: 0 | E6: 0 | F6: Toujours présent | G6: 1
C7: Sarobidy | D7: 2 | E7: 46193 | F7: Toujours présent | G7: 1
C8: Davida | D8: 1 | E8: 46186 | F8: Marary | G8: 1
C9: Mandresy | D9: 1 | E9: 46207 | F9: Toujours présent | G9: 1
C10: Manoa | D10: 0 | E10: 0 | F10: Toujours présent | G10: 1
C11: Irina | D11: Jamais present 0 | E11: 0 | F11: injustifier | G11: -3

Sheet Sheet13
A1: Membre | B1: Role | C1: Temps(min) | D1: temps(heures) | E1: tarif horaire | F1: Budget Total
A2: Miaro | B2: Dev Junior | C2: 440 | D2: 7.33 | E2: 20000 | F2: =(C2/60)*E2 -> 146666.67
A3: Davida | B3: Dev Junior | C3: 995 | D3: 16.33 | E3: 20000 | F3: =(C3/60)*E3 -> 331666.67
A4: Fanilo | B4: Dev Junior | C4: 1400 | D4: 23.33 | E4: 20000 | F4: =(C4/60)*E4 -> 466666.67
A5: Sarobidy | B5: Dev Junior | C5: 750 | D5: 12.5 | E5: 20000 | F5: =(C5/60)*E5 -> 250000
A6: Tsanta | B6: Dev Junior | C6: 990 | D6: 16.5 | E6: 20000 | F6: =(C6/60)*E6 -> 330000
A7: Mickaella | B7: Chef de Projet | C7: 760 | D7: 12.67 | E7: 25000 | F7: =(C7/60)*E7 -> 316666.67
A8: Manoa | B8: Dev Junior | C8: 840 | D8: 14 | E8: 20000 | F8: =(C8/60)*E8 -> 280000
A9: Noah | B9: Dev Junior | C9: 1020 | D9: 17 | E9: 20000 | F9: =(C9/60)*E9 -> 340000
F10: =SUM(F2:F9) -> 2461666.7
